task3/ram2ports.sv
module ram2ports #(
    parameter   ADDRESS_WIDTH = 8,
                DATA_WIDTH = 8
)(
    input logic                                 clk,
    input logic                                 wr_en,
    input logic                                 rd_en,
    input logic     [ADDRESS_WIDTH-1:0]         wr_addr,
    input logic     [ADDRESS_WIDTH-1:0]         rd_addr,
    output logic     [DATA_WIDTH-1:0]           din,
    output logic     [DATA_WIDTH-1:0]           dout
);

logic [DATA_WIDTH-1:0] ram_array [2**ADDRESS_WIDTH-1:0];

always_ff @(posedge clk) begin
    if (wr_en == 1'b1)
        ram_array[wr_addr] <= din;
    if (rd_en == 1'b1)
        // output is synchronous
        dout <= ram_array [rd_addr];
end

endmodule

task1/counter.sv
module counter #(
    parameter WIDTH = 8
)(
    // interface signals
    input logic                    clk, //clock
    input logic                    rst, //reset
    input logic                    en,  //counter enable
    input logic  [WIDTH-1:0]       incr, // additional input 
    output logic [WIDTH-1:0]       count //count output
);

always_ff @ (posedge clk)
    if (rst) count <= {WIDTH{1'b0}};
    else     count <= count + incr + {{WIDTH-1{1'b0}}, en};

endmodule

task3/sigdelay.sv
module sigdelay #(
    parameter   A_WIDTH = 8,
                D_WIDTH = 8
)(
    // interface signals
    input   logic               clk,        
    input   logic               rst,        
    input   logic               en,              
    input   logic               wr,         
    input   logic               rd,         
    input   logic [D_WIDTH-1:0] offset,       
    input  logic [D_WIDTH-1:0]  wr_addr,
    output  logic [D_WIDTH-1:0] mic_signal,        
    output  logic [D_WIDTH-1:0] delayed_signal       
);

    logic   [A_WIDTH-1:0]       address;    // interconnect wire

counter addrCounter (
    .clk (clk),
    .rst (rst),
    .en (en),
    .incr (offset),
    .count (address)
);

ram2ports micRam (
    .wr_en (wr),
    .rd_en (rd),
    .wr_addr (wr_addr),
    .rd_addr (offset),
    .din (mic_signal),
    .dout (delayed_signal)
);

endmodule

task3/sigdelay.vcd
$version Generated by VerilatedVcd $end
$date Wed Nov  9 01:17:38 2022 $end
$timescale 1ps $end

 $scope module TOP $end
  $var wire  1 # clk $end
  $var wire  8 + delayed_signal [7:0] $end
  $var wire  1 % en $end
  $var wire  8 * mic_signal [7:0] $end
  $var wire  8 ( offset [7:0] $end
  $var wire  1 ' rd $end
  $var wire  1 $ rst $end
  $var wire  1 & wr $end
  $var wire  8 ) wr_addr [7:0] $end
  $scope module sigdelay $end
   $var wire 32 - A_WIDTH [31:0] $end
   $var wire 32 - D_WIDTH [31:0] $end
   $var wire  8 , address [7:0] $end
   $var wire  1 # clk $end
   $var wire  8 + delayed_signal [7:0] $end
   $var wire  1 % en $end
   $var wire  8 * mic_signal [7:0] $end
   $var wire  8 ( offset [7:0] $end
   $var wire  1 ' rd $end
   $var wire  1 $ rst $end
   $var wire  1 & wr $end
   $var wire  8 ) wr_addr [7:0] $end
   $scope module addrCounter $end
    $var wire 32 - WIDTH [31:0] $end
    $var wire  1 # clk $end
    $var wire  8 , count [7:0] $end
    $var wire  1 % en $end
    $var wire  8 ( incr [7:0] $end
    $var wire  1 $ rst $end
   $upscope $end
   $scope module micRam $end
    $var wire 32 - ADDRESS_WIDTH [31:0] $end
    $var wire 32 - DATA_WIDTH [31:0] $end
    $var wire  1 . clk $end
    $var wire  8 * din [7:0] $end
    $var wire  8 + dout [7:0] $end
    $var wire  8 ( rd_addr [7:0] $end
    $var wire  1 ' rd_en $end
    $var wire  8 ) wr_addr [7:0] $end
    $var wire  1 & wr_en $end
   $upscope $end
  $upscope $end
 $upscope $end
$enddefinitions $end


#0
1#
0$
0%
1&
1'
b01000000 (
b00000000 )
b00000000 *
b00000000 +
b00000000 ,
b00000000000000000000000000001000 -
0.
#1
0#
#2
1#
b01100100 (
b01101110 *
b01000000 ,
#3
0#
#4
1#
b01110000 *
b10100100 ,
#5
0#
#6
1#
b01101101 *
b00001000 ,
#7
0#
#8
1#
b01101100 ,
#9
0#
#10
1#
b01110001 *
b11010000 ,
#11
0#
#12
1#
b01101111 *
b00110100 ,
#13
0#
#14
1#
b01110000 *
b10011000 ,
#15
0#
#16
1#
b01101111 *
b11111100 ,
#17
0#
#18
1#
b01101100 *
b01100000 ,
#19
0#
#20
1#
b01110000 *
b11000100 ,
#21
0#
#22
1#
b00101000 ,
#23
0#
#24
1#
b01101111 *
b10001100 ,
#25
0#
#26
1#
b01101110 *
b11110000 ,
#27
0#
#28
1#
b01101100 *
b01010100 ,
#29
0#
#30
1#
b01101101 *
b10111000 ,
#31
0#
#32
1#
b01101111 *
b00011100 ,
#33
0#
#34
1#
b01110001 *
b10000000 ,
#35
0#
#36
1#
b01101110 *
b11100100 ,
#37
0#
#38
1#
b01001000 ,
#39
0#
#40
1#
b01110000 *
b10101100 ,
#41
0#
#42
1#
b00010000 ,
#43
0#
#44
1#
b01110001 *
b01110100 ,
#45
0#
#46
1#
b01101111 *
b11011000 ,
#47
0#
#48
1#
b01110001 *
b00111100 ,
#49
0#
#50
1#
b10100000 ,
#51
0#
#52
1#
b01110010 *
b00000100 ,
#53
0#
#54
1#
b01110001 *
b01101000 ,
#55
0#
#56
1#
b01110000 *
b11001100 ,
#57
0#
#58
1#
b00110000 ,
#59
0#
#60
1#
b01101110 *
b10010100 ,
#61
0#
#62
1#
b01101111 *
b11111000 ,
#63
0#
#64
1#
b01011100 ,
#65
0#
#66
1#
b01110000 *
b11000000 ,
#67
0#
#68
1#
b01101110 *
b00100100 ,
#69
0#
#70
1#
b10001000 ,
#71
0#
#72
1#
b01110000 *
b11101100 ,
#73
0#
#74
1#
b01010000 ,
#75
0#
#76
1#
b10110100 ,
#77
0#
#78
1#
b01101100 *
b00011000 ,
#79
0#
#80
1#
b01110000 *
b01111100 ,
#81
0#
#82
1#
b01101110 *
b11100000 ,
#83
0#
#84
1#
b01110000 *
b01000100 ,
#85
0#
#86
1#
b10101000 ,
#87
0#
#88
1#
b01110001 *
b00001100 ,
#89
0#
#90
1#
b01110000 ,
#91
0#
#92
1#
b11010100 ,
#93
0#
#94
1#
b00111000 ,
#95
0#
#96
1#
b10011100 ,
#97
0#
#98
1#
b01101111 *
b00000000 ,
#99
0#
#100
1#
b01110000 *
b01100100 ,
#101
0#
#102
1#
b01101111 *
b11001000 ,
#103
0#
#104
1#
b01110000 *
b00101100 ,
#105
0#
#106
1#
b01101111 *
b10010000 ,
#107
0#
#108
1#
b01101110 *
b11110100 ,
#109
0#
#110
1#
b01101111 *
b01011000 ,
#111
0#
#112
1#
b01101110 *
b10111100 ,
#113
0#
#114
1#
b01110000 *
b00100000 ,
#115
0#
#116
1#
b01110001 *
b10000100 ,
#117
0#
#118
1#
b11101000 ,
#119
0#
#120
1#
b01101110 *
b01001100 ,
#121
0#
#122
1#
b01101111 *
b10110000 ,
#123
0#
#124
1#
b01101101 *
b00010100 ,
#125
0#
#126
1#
b01101110 *
b01111000 ,
#127
0#
#128
1#
b01101111 *
b11011100 ,
#129
0#
#130
1#
b01101110 *
b01000000 ,
#131
0#
#132
1#
b01101111 *
b10100100 ,
#133
0#
#134
1#
b00001000 ,
#135
0#
#136
1#
b01101100 *
b01101100 ,
#137
0#
#138
1#
b01101110 *
b11010000 ,
#139
0#
#140
1#
b01101101 *
b00110100 ,
#141
0#
#142
1#
b01101110 *
b10011000 ,
#143
0#
#144
1#
b11111100 ,
#145
0#
#146
1#
b01101111 *
b01100000 ,
#147
0#
#148
1#
b01110000 *
b11000100 ,
#149
0#
#150
1#
b01101111 *
b00101000 ,
#151
0#
#152
1#
b10001100 ,
#153
0#
#154
1#
b11110000 ,
#155
0#
#156
1#
b01101110 *
b01010100 ,
#157
0#
#158
1#
b10111000 ,
#159
0#
#160
1#
b00011100 ,
#161
0#
#162
1#
b01101111 *
b10000000 ,
#163
0#
#164
1#
b01110000 *
b11100100 ,
#165
0#
#166
1#
b01101101 *
b01001000 ,
#167
0#
#168
1#
b01101111 *
b10101100 ,
#169
0#
#170
1#
b01101101 *
b00010000 ,
#171
0#
#172
1#
b01101111 *
b01110100 ,
#173
0#
#174
1#
b01110000 *
b11011000 ,
#175
0#
#176
1#
b01101011 *
b00111100 ,
#177
0#
#178
1#
b01101110 *
b10100000 ,
#179
0#
#180
1#
b01101101 *
b00000100 ,
#181
0#
#182
1#
b01101110 *
b01101000 ,
#183
0#
#184
1#
b01101101 *
b11001100 ,
#185
0#
#186
1#
b01110000 *
b00110000 ,
#187
0#
#188
1#
b01101110 *
b10010100 ,
#189
0#
#190
1#
b11111000 ,
#191
0#
#192
1#
b01110000 *
b01011100 ,
#193
0#
#194
1#
b01101110 *
b11000000 ,
#195
0#
#196
1#
b01101111 *
b00100100 ,
#197
0#
#198
1#
b01101110 *
b10001000 ,
#199
0#
#200
1#
b01110001 *
b11101100 ,
#201
0#
#202
1#
b01110000 *
b01010000 ,
#203
0#
#204
1#
b01101100 *
b10110100 ,
#205
0#
#206
1#
b01110000 *
b00011000 ,
#207
0#
#208
1#
b01101110 *
b01111100 ,
#209
0#
#210
1#
b11100000 ,
#211
0#
#212
1#
b01000100 ,
#213
0#
#214
1#
b01101101 *
b10101000 ,
#215
0#
#216
1#
b00001100 ,
#217
0#
#218
1#
b01110000 ,
#219
0#
#220
1#
b01101100 *
b11010100 ,
#221
0#
#222
1#
b01101111 *
b00111000 ,
#223
0#
#224
1#
b10011100 ,
#225
0#
#226
1#
b01101110 *
b00000000 ,
#227
0#
#228
1#
b01101111 *
b01100100 ,
#229
0#
#230
1#
b11001000 ,
#231
0#
#232
1#
b00101100 ,
#233
0#
#234
1#
b01101110 *
b10010000 ,
#235
0#
#236
1#
b01101101 *
b11110100 ,
#237
0#
#238
1#
b01011000 ,
#239
0#
#240
1#
b01101110 *
b10111100 ,
#241
0#
#242
1#
b01101011 *
b00100000 ,
#243
0#
#244
1#
b01101101 *
b10000100 ,
#245
0#
#246
1#
b01101111 *
b11101000 ,
#247
0#
#248
1#
b01101110 *
b01001100 ,
#249
0#
#250
1#
b01101111 *
b10110000 ,
#251
0#
#252
1#
b01101101 *
b00010100 ,
#253
0#
#254
1#
b01111000 ,
#255
0#
#256
1#
b01101111 *
b11011100 ,
#257
0#
#258
1#
b01101110 *
b01000000 ,
#259
0#
#260
1#
b01101101 *
b10100100 ,
#261
0#
#262
1#
b00001000 ,
#263
0#
#264
1#
b01101100 *
b01101100 ,
#265
0#
#266
1#
b01101110 *
b11010000 ,
#267
0#
#268
1#
b00110100 ,
#269
0#
#270
1#
b01101101 *
b10011000 ,
#271
0#
#272
1#
b01101110 *
b11111100 ,
#273
0#
#274
1#
b01100000 ,
#275
0#
#276
1#
b11000100 ,
#277
0#
#278
1#
b01110001 *
b00101000 ,
#279
0#
#280
1#
b01101111 *
b10001100 ,
#281
0#
#282
1#
b01110001 *
b11110000 ,
#283
0#
#284
1#
b01101111 *
b01010100 ,
#285
0#
#286
1#
b01101100 *
b10111000 ,
#287
0#
#288
1#
b01101110 *
b00011100 ,
#289
0#
#290
1#
b10000000 ,
#291
0#
#292
1#
b11100100 ,
#293
0#
#294
1#
b01101111 *
b01001000 ,
#295
0#
#296
1#
b01110001 *
b10101100 ,
#297
0#
#298
1#
b01101101 *
b00010000 ,
#299
0#
#300
1#
b01101100 *
b01110100 ,
#301
0#
#302
1#
b01101101 *
b11011000 ,
#303
0#
#304
1#
b01101110 *
b00111100 ,
#305
0#
#306
1#
b01101101 *
b10100000 ,
#307
0#
#308
1#
b00000100 ,
#309
0#
#310
1#
b01101100 *
b01101000 ,
#311
0#
#312
1#
b01101110 *
b11001100 ,
#313
0#
#314
1#
b01101100 *
b00110000 ,
#315
0#
#316
1#
b01101111 *
b10010100 ,
#317
0#
#318
1#
b01101110 *
b11111000 ,
#319
0#
#320
1#
b01110001 *
b01011100 ,
#321
0#
#322
1#
b01101111 *
b11000000 ,
#323
0#
#324
1#
b01110000 *
b00100100 ,
#325
0#
#326
1#
b01101110 *
b10001000 ,
#327
0#
#328
1#
b01101101 *
b11101100 ,
#329
0#
#330
1#
b01010000 ,
#331
0#
#332
1#
b01101100 *
b10110100 ,
#333
0#
#334
1#
b01101110 *
b00011000 ,
#335
0#
#336
1#
b01101100 *
b01111100 ,
#337
0#
#338
1#
b01101111 *
b11100000 ,
#339
0#
#340
1#
b01000100 ,
#341
0#
#342
1#
b10101000 ,
#343
0#
#344
1#
b01101110 *
b00001100 ,
#345
0#
#346
1#
b01101101 *
b01110000 ,
#347
0#
#348
1#
b01101110 *
b11010100 ,
#349
0#
#350
1#
b01101101 *
b00111000 ,
#351
0#
#352
1#
b01101111 *
b10011100 ,
#353
0#
#354
1#
b00000000 ,
#355
0#
#356
1#
b01101101 *
b01100100 ,
#357
0#
#358
1#
b11001000 ,
#359
0#
#360
1#
b01101110 *
b00101100 ,
#361
0#
#362
1#
b10010000 ,
#363
0#
#364
1#
b01101111 *
b11110100 ,
#365
0#
#366
1#
b01101110 *
b01011000 ,
#367
0#
#368
1#
b10111100 ,
#369
0#
#370
1#
b01110000 *
b00100000 ,
#371
0#
#372
1#
b01101111 *
b10000100 ,
#373
0#
#374
1#
b11101000 ,
#375
0#
#376
1#
b01101110 *
b01001100 ,
#377
0#
#378
1#
b01101101 *
b10110000 ,
#379
0#
#380
1#
b01101110 *
b00010100 ,
#381
0#
#382
1#
b01111000 ,
#383
0#
#384
1#
b01101101 *
b11011100 ,
#385
0#
#386
1#
b01110000 *
b01000000 ,
#387
0#
#388
1#
b01101100 *
b10100100 ,
#389
0#
#390
1#
b01101110 *
b00001000 ,
#391
0#
#392
1#
b01101100 ,
#393
0#
#394
1#
b11010000 ,
#395
0#
#396
1#
b01110000 *
b00110100 ,
#397
0#
#398
1#
b01101111 *
b10011000 ,
#399
0#
#400
1#
b01110000 *
b11111100 ,
#401
0#
#402
1#
b01101110 *
b01100000 ,
#403
0#
#404
1#
b11000100 ,
#405
0#
#406
1#
b01101101 *
b00101000 ,
#407
0#
#408
1#
b10001100 ,
#409
0#
#410
1#
b01101111 *
b11110000 ,
#411
0#
#412
1#
b01101110 *
b01010100 ,
#413
0#
#414
1#
b01101111 *
b10111000 ,
#415
0#
#416
1#
b01101110 *
b00011100 ,
#417
0#
#418
1#
b10000000 ,
#419
0#
#420
1#
b01101111 *
b11100100 ,
#421
0#
#422
1#
b01101110 *
b01001000 ,
#423
0#
#424
1#
b01101111 *
b10101100 ,
#425
0#
#426
1#
b01101101 *
b00010000 ,
#427
0#
#428
1#
b01110100 ,
#429
0#
#430
1#
b01101110 *
b11011000 ,
#431
0#
#432
1#
b01101111 *
b00111100 ,
#433
0#
#434
1#
b10100000 ,
#435
0#
#436
1#
b01101110 *
b00000100 ,
#437
0#
#438
1#
b01101000 ,
#439
0#
#440
1#
b01110000 *
b11001100 ,
#441
0#
#442
1#
b01101111 *
b00110000 ,
#443
0#
#444
1#
b10010100 ,
#445
0#
#446
1#
b01110001 *
b11111000 ,
#447
0#
#448
1#
b01110010 *
b01011100 ,
#449
0#
#450
1#
b01110001 *
b11000000 ,
#451
0#
#452
1#
b01110000 *
b00100100 ,
#453
0#
#454
1#
b01101111 *
b10001000 ,
#455
0#
#456
1#
b01101110 *
b11101100 ,
#457
0#
#458
1#
b01010000 ,
#459
0#
#460
1#
b10110100 ,
#461
0#
#462
1#
b01110000 *
b00011000 ,
#463
0#
#464
1#
b01111100 ,
#465
0#
#466
1#
b01101110 *
b11100000 ,
#467
0#
#468
1#
b01110000 *
b01000100 ,
#469
0#
#470
1#
b01101110 *
b10101000 ,
#471
0#
#472
1#
b00001100 ,
#473
0#
#474
1#
b01101111 *
b01110000 ,
#475
0#
#476
1#
b11010100 ,
#477
0#
#478
1#
b01110010 *
b00111000 ,
#479
0#
#480
1#
b01110000 *
b10011100 ,
#481
0#
#482
1#
b01101100 *
b00000000 ,
#483
0#
#484
1#
b01101111 *
b01100100 ,
#485
0#
#486
1#
b01101110 *
b11001000 ,
#487
0#
#488
1#
b01101111 *
b00101100 ,
#489
0#
#490
1#
b10010000 ,
#491
0#
#492
1#
b01110000 *
b11110100 ,
#493
0#
#494
1#
b01101101 *
b01011000 ,
#495
0#
#496
1#
b01101111 *
b10111100 ,
#497
0#
#498
1#
b01110000 *
b00100000 ,
#499
0#
#500
1#
b01101110 *
b10000100 ,
#501
0#
#502
1#
b01101111 *
b11101000 ,
#503
0#
#504
1#
b01101110 *
b01001100 ,
#505
0#
#506
1#
b01110000 *
b10110000 ,
#507
0#
#508
1#
b01101111 *
b00010100 ,
#509
0#
#510
1#
b01111000 ,
#511
0#
#512
1#
b11011100 ,
#513
0#
#514
1#
b01000000 ,
#515
0#
#516
1#
b01110000 *
b10100100 ,
#517
0#
#518
1#
b01101111 *
b00001000 ,
#519
0#
#520
1#
b01101101 *
b01101100 ,
#521
0#
#522
1#
b01101111 *
b11010000 ,
#523
0#
#524
1#
b00110100 ,
#525
0#
#526
1#
b01110010 *
b10011000 ,
#527
0#
#528
1#
b01101111 *
b11111100 ,
#529
0#
#530
1#
b01110010 *
b01100000 ,
#531
0#
#532
1#
b01110000 *
b11000100 ,
#533
0#
#534
1#
b00101000 ,
#535
0#
#536
1#
b01101111 *
b10001100 ,
#537
0#
#538
1#
b01101101 *
b11110000 ,
#539
0#
#540
1#
b01101111 *
b01010100 ,
#541
0#
#542
1#
b01101101 *
b10111000 ,
#543
0#
#544
1#
b01101110 *
b00011100 ,
#545
0#
#546
1#
b01101100 *
b10000000 ,
#547
0#
#548
1#
b01101110 *
b11100100 ,
#549
0#
#550
1#
b01101111 *
b01001000 ,
#551
0#
#552
1#
b01101110 *
b10101100 ,
#553
0#
#554
1#
b01101101 *
b00010000 ,
#555
0#
#556
1#
b01101110 *
b01110100 ,
#557
0#
#558
1#
b01101111 *
b11011000 ,
#559
0#
#560
1#
b00111100 ,
#561
0#
#562
1#
b01110001 *
b10100000 ,
#563
0#
#564
1#
b01110000 *
b00000100 ,
#565
0#
#566
1#
b01101110 *
b01101000 ,
#567
0#
#568
1#
b01101101 *
b11001100 ,
#569
0#
#570
1#
b01101110 *
b00110000 ,
#571
0#
#572
1#
b01101100 *
b10010100 ,
#573
0#
#574
1#
b11111000 ,
#575
0#
#576
1#
b01101111 *
b01011100 ,
#577
0#
#578
1#
b01101110 *
b11000000 ,
#579
0#
#580
1#
b00100100 ,
#581
0#
#582
1#
b01101101 *
b10001000 ,
#583
0#
#584
1#
b01110001 *
b11101100 ,
#585
0#
#586
1#
b01110000 *
b01010000 ,
#587
0#
#588
1#
b01101110 *
b10110100 ,
#589
0#
#590
1#
b00011000 ,
#591
0#
#592
1#
b01111100 ,
#593
0#
#594
1#
b01110000 *
b11100000 ,
#595
0#
#596
1#
b01101110 *
b01000100 ,
#597
0#
#598
1#
b01101100 *
b10101000 ,
#599
0#
#600
1#
b00001100 ,
#601
0#
#602
1#
b01110000 *
b01110000 ,
#603
0#
#604
1#
b01101110 *
b11010100 ,
#605
0#
#606
1#
b01101101 *
b00111000 ,
#607
0#
#608
1#
b01101111 *
b10011100 ,
#609
0#
#610
1#
b01110001 *
b00000000 ,
#611
0#
#612
1#
b01100100 ,
#613
0#
#614
1#
b01101111 *
b11001000 ,
#615
0#
#616
1#
b01110000 *
b00101100 ,
#617
0#
#618
1#
b01110001 *
b10010000 ,
#619
0#
#620
1#
b01110000 *
b11110100 ,
#621
0#
#622
1#
b01101100 *
b01011000 ,
#623
0#
#624
1#
b01101110 *
b10111100 ,
#625
0#
#626
1#
b01101111 *
b00100000 ,
#627
0#
#628
1#
b01110000 *
b10000100 ,
#629
0#
#630
1#
b11101000 ,
#631
0#
#632
1#
b01101110 *
b01001100 ,
#633
0#
#634
1#
b01110000 *
b10110000 ,
#635
0#
#636
1#
b01110001 *
b00010100 ,
#637
0#
#638
1#
b01110000 *
b01111000 ,
#639
0#
#640
1#
b11011100 ,
#641
0#
#642
1#
b01101110 *
b01000000 ,
#643
0#
#644
1#
b01110001 *
b10100100 ,
#645
0#
#646
1#
b01110000 *
b00001000 ,
#647
0#
#648
1#
b01101110 *
b01101100 ,
#649
0#
#650
1#
b01101111 *
b11010000 ,
#651
0#
#652
1#
b01110000 *
b00110100 ,
#653
0#
#654
1#
b01101110 *
b10011000 ,
#655
0#
#656
1#
b01101111 *
b11111100 ,
#657
0#
#658
1#
b01101101 *
b01100000 ,
#659
0#
#660
1#
b11000100 ,
#661
0#
#662
1#
b01101110 *
b00101000 ,
#663
0#
#664
1#
b10001100 ,
#665
0#
#666
1#
b01101111 *
b11110000 ,
#667
0#
#668
1#
b01110001 *
b01010100 ,
#669
0#
#670
1#
b10111000 ,
#671
0#
#672
1#
b01101111 *
b00011100 ,
#673
0#
#674
1#
b01110000 *
b10000000 ,
#675
0#
#676
1#
b01101101 *
b11100100 ,
#677
0#
#678
1#
b01101111 *
b01001000 ,
#679
0#
#680
1#
b01101110 *
b10101100 ,
#681
0#
#682
1#
b01110000 *
b00010000 ,
#683
0#
#684
1#
b01110100 ,
#685
0#
#686
1#
b01101111 *
b11011000 ,
#687
0#
#688
1#
b01110001 *
b00111100 ,
#689
0#
#690
1#
b01101110 *
b10100000 ,
#691
0#
#692
1#
b01101111 *
b00000100 ,
#693
0#
#694
1#
b01110000 *
b01101000 ,
#695
0#
#696
1#
b01101111 *
b11001100 ,
#697
0#
#698
1#
b01110001 *
b00110000 ,
#699
0#
#700
1#
b01101111 *
b10010100 ,
#701
0#
#702
1#
b01101100 *
b11111000 ,
#703
0#
#704
1#
b01101110 *
b01011100 ,
#705
0#
#706
1#
b01101111 *
b11000000 ,
#707
0#
#708
1#
b01101110 *
b00100100 ,
#709
0#
#710
1#
b01110000 *
b10001000 ,
#711
0#
#712
1#
b01101110 *
b11101100 ,
#713
0#
#714
1#
b01101111 *
b01010000 ,
#715
0#
#716
1#
b01101101 *
b10110100 ,
#717
0#
#718
1#
b01101111 *
b00011000 ,
#719
0#
#720
1#
b01111100 ,
#721
0#
#722
1#
b01101101 *
b11100000 ,
#723
0#
#724
1#
b01110001 *
b01000100 ,
#725
0#
#726
1#
b01101100 *
b10101000 ,
#727
0#
#728
1#
b01101101 *
b00001100 ,
#729
0#
#730
1#
b01101111 *
b01110000 ,
#731
0#
#732
1#
b11010100 ,
#733
0#
#734
1#
b01101110 *
b00111000 ,
#735
0#
#736
1#
b01101101 *
b10011100 ,
#737
0#
#738
1#
b01101110 *
b00000000 ,
#739
0#
#740
1#
b01101101 *
b01100100 ,
#741
0#
#742
1#
b11001000 ,
#743
0#
#744
1#
b01101111 *
b00101100 ,
#745
0#
#746
1#
b10010000 ,
#747
0#
#748
1#
b01110001 *
b11110100 ,
#749
0#
#750
1#
b01101111 *
b01011000 ,
#751
0#
#752
1#
b01101110 *
b10111100 ,
#753
0#
#754
1#
b01101111 *
b00100000 ,
#755
0#
#756
1#
b01101101 *
b10000100 ,
#757
0#
#758
1#
b11101000 ,
#759
0#
#760
1#
b01101100 *
b01001100 ,
#761
0#
#762
1#
b01110001 *
b10110000 ,
#763
0#
#764
1#
b01110010 *
b00010100 ,
#765
0#
#766
1#
b01101110 *
b01111000 ,
#767
0#
#768
1#
b01110000 *
b11011100 ,
#769
0#
#770
1#
b01101110 *
b01000000 ,
#771
0#
#772
1#
b01101111 *
b10100100 ,
#773
0#
#774
1#
b01101110 *
b00001000 ,
#775
0#
#776
1#
b01110000 *
b01101100 ,
#777
0#
#778
1#
b01101111 *
b11010000 ,
#779
0#
#780
1#
b01110001 *
b00110100 ,
#781
0#
#782
1#
b01101110 *
b10011000 ,
#783
0#
#784
1#
b01110001 *
b11111100 ,
#785
0#
#786
1#
b01101110 *
b01100000 ,
#787
0#
#788
1#
b01110000 *
b11000100 ,
#789
0#
#790
1#
b01101110 *
b00101000 ,
#791
0#
#792
1#
b01101101 *
b10001100 ,
#793
0#
#794
1#
b01101100 *
b11110000 ,
#795
0#
#796
1#
b01101110 *
b01010100 ,
#797
0#
#798
1#
b01101010 *
b10111000 ,
#799
0#
#800
1#
b01101110 *
b00011100 ,
#801
0#
#802
1#
b01110000 *
b10000000 ,
#803
0#
#804
1#
b01101110 *
b11100100 ,
#805
0#
#806
1#
b01101111 *
b01001000 ,
#807
0#
#808
1#
b01110000 *
b10101100 ,
#809
0#
#810
1#
b01101111 *
b00010000 ,
#811
0#
#812
1#
b01110100 ,
#813
0#
#814
1#
b01101110 *
b11011000 ,
#815
0#
#816
1#
b01110000 *
b00111100 ,
#817
0#
#818
1#
b01101111 *
b10100000 ,
#819
0#
#820
1#
b01101101 *
b00000100 ,
#821
0#
#822
1#
b01101011 *
b01101000 ,
#823
0#
#824
1#
b01101110 *
b11001100 ,
#825
0#
#826
1#
b00110000 ,
#827
0#
#828
1#
b01101011 *
b10010100 ,
#829
0#
#830
1#
b01101111 *
b11111000 ,
#831
0#
#832
1#
b01011100 ,
#833
0#
#834
1#
b01101110 *
b11000000 ,
#835
0#
#836
1#
b00100100 ,
#837
0#
#838
1#
b01101101 *
b10001000 ,
#839
0#
#840
1#
b01110000 *
b11101100 ,
#841
0#
#842
1#
b01101111 *
b01010000 ,
#843
0#
#844
1#
b01110000 *
b10110100 ,
#845
0#
#846
1#
b01110001 *
b00011000 ,
#847
0#
#848
1#
b01101110 *
b01111100 ,
#849
0#
#850
1#
b11100000 ,
#851
0#
#852
1#
b01000100 ,
#853
0#
#854
1#
b01101101 *
b10101000 ,
#855
0#
#856
1#
b01110000 *
b00001100 ,
#857
0#
#858
1#
b01101111 *
b01110000 ,
#859
0#
#860
1#
b01101110 *
b11010100 ,
#861
0#
#862
1#
b01101101 *
b00111000 ,
#863
0#
#864
1#
b10011100 ,
#865
0#
#866
1#
b00000000 ,
#867
0#
#868
1#
b01110001 *
b01100100 ,
#869
0#
#870
1#
b01101101 *
b11001000 ,
#871
0#
#872
1#
b01101110 *
b00101100 ,
#873
0#
#874
1#
b01101100 *
b10010000 ,
#875
0#
#876
1#
b01101111 *
b11110100 ,
#877
0#
#878
1#
b01011000 ,
#879
0#
#880
1#
b01101100 *
b10111100 ,
#881
0#
#882
1#
b00100000 ,
#883
0#
#884
1#
b01101111 *
b10000100 ,
#885
0#
#886
1#
b01101110 *
b11101000 ,
#887
0#
#888
1#
b01001100 ,
#889
0#
#890
1#
b01101111 *
b10110000 ,
#891
0#
#892
1#
b01101101 *
b00010100 ,
#893
0#
#894
1#
b01110000 *
b01111000 ,
#895
0#
#896
1#
b11011100 ,
#897
0#
#898
1#
b01101110 *
b01000000 ,
#899
0#
#900
1#
b01110000 *
b10100100 ,
#901
0#
#902
1#
b01101110 *
b00001000 ,
#903
0#
#904
1#
b01101101 *
b01101100 ,
#905
0#
#906
1#
b01101110 *
b11010000 ,
#907
0#
#908
1#
b01101101 *
b00110100 ,
#909
0#
#910
1#
b10011000 ,
#911
0#
#912
1#
b01101110 *
b11111100 ,
#913
0#
#914
1#
b01101101 *
b01100000 ,
#915
0#
#916
1#
b01110001 *
b11000100 ,
#917
0#
#918
1#
b01101110 *
b00101000 ,
#919
0#
#920
1#
b01101111 *
b10001100 ,
#921
0#
#922
1#
b01110000 *
b11110000 ,
#923
0#
#924
1#
b01101100 *
b01010100 ,
#925
0#
#926
1#
b01101111 *
b10111000 ,
#927
0#
#928
1#
b00011100 ,
#929
0#
#930
1#
b01101110 *
b10000000 ,
#931
0#
#932
1#
b01101100 *
b11100100 ,
#933
0#
#934
1#
b01101110 *
b01001000 ,
#935
0#
#936
1#
b01101101 *
b10101100 ,
#937
0#
#938
1#
b00010000 ,
#939
0#
#940
1#
b01101110 *
b01110100 ,
#941
0#
#942
1#
b01101101 *
b11011000 ,
#943
0#
#944
1#
b01101110 *
b00111100 ,
#945
0#
#946
1#
b01110000 *
b10100000 ,
#947
0#
#948
1#
b01101111 *
b00000100 ,
#949
0#
#950
1#
b01101110 *
b01101000 ,
#951
0#
#952
1#
b01110001 *
b11001100 ,
#953
0#
#954
1#
b01101111 *
b00110000 ,
#955
0#
#956
1#
b01101110 *
b10010100 ,
#957
0#
#958
1#
b11111000 ,
#959
0#
#960
1#
b01101011 *
b01011100 ,
#961
0#
#962
1#
b01101100 *
b11000000 ,
#963
0#
#964
1#
b01110000 *
b00100100 ,
#965
0#
#966
1#
b01101101 *
b10001000 ,
#967
0#
#968
1#
b01110001 *
b11101100 ,
#969
0#
#970
1#
b01101100 *
b01010000 ,
#971
0#
#972
1#
b01110000 *
b10110100 ,
#973
0#
#974
1#
b01101111 *
b00011000 ,
#975
0#
#976
1#
b01111100 ,
#977
0#
#978
1#
b01110000 *
b11100000 ,
#979
0#
#980
1#
b01101111 *
b01000100 ,
#981
0#
#982
1#
b01110001 *
b10101000 ,
#983
0#
#984
1#
b01110000 *
b00001100 ,
#985
0#
#986
1#
b01101111 *
b01110000 ,
#987
0#
#988
1#
b01101101 *
b11010100 ,
#989
0#
#990
1#
b01101110 *
b00111000 ,
#991
0#
#992
1#
b10011100 ,
#993
0#
#994
1#
b01101111 *
b00000000 ,
#995
0#
#996
1#
b01100100 ,
#997
0#
#998
1#
b01101110 *
b11001000 ,
#999
0#
#1000
1#
b00101100 ,
#1001
0#
#1002
1#
b10010000 ,
#1003
0#
#1004
1#
b01110001 *
b11110100 ,
#1005
0#
#1006
1#
b01110000 *
b01011000 ,
#1007
0#
#1008
1#
b10111100 ,
#1009
0#
#1010
1#
b01110010 *
b00100000 ,
#1011
0#
#1012
1#
b01110000 *
b10000100 ,
#1013
0#
#1014
1#
b01101111 *
b11101000 ,
#1015
0#
#1016
1#
b01101101 *
b01001100 ,
#1017
0#
#1018
1#
b01101111 *
b10110000 ,
#1019
0#
#1020
1#
b01101110 *
b00010100 ,
#1021
0#
#1022
1#
b01101111 *
b01111000 ,
#1023
0#
#1024
1#
b11011100 ,
#1025
0#
#1026
1#
b10101001 *
b01000000 ,
#1027
0#
#1028
1#
b10110100 *
b10100100 ,
#1029
0#
